CHANGES.txt
MANIFEST.in
README.txt
setup.py
src/cykooz/__init__.py
src/cykooz.title.egg-info/PKG-INFO
src/cykooz.title.egg-info/SOURCES.txt
src/cykooz.title.egg-info/dependency_links.txt
src/cykooz.title.egg-info/namespace_packages.txt
src/cykooz.title.egg-info/not-zip-safe
src/cykooz.title.egg-info/requires.txt
src/cykooz.title.egg-info/top_level.txt
src/cykooz/title/__init__.py
src/cykooz/title/adapters.py
src/cykooz/title/configure.zcml
src/cykooz/title/i18n.py
src/cykooz/title/interfaces.py
src/cykooz/title/tests.py
src/cykooz/title/title.txt
src/cykooz/title/locales/cykooz.title.pot
src/cykooz/title/locales/ru/LC_MESSAGES/cykooz.title.mo
src/cykooz/title/locales/ru/LC_MESSAGES/cykooz.title.po