Metadata-Version: 1.0
Name: cykooz.title
Version: 1.0.0
Summary: Adapters for adapting any object to ITitle interface.
Home-page: https://bitbucket.org/cykooz/cykooz.title
Author: Cykooz
Author-email: saikuz@mail.ru
License: ZPL
Keywords: zope3
Platform: UNKNOWN
Classifier: Development Status :: 4 - Beta
Classifier: Environment :: Web Environment
Classifier: Intended Audience :: Developers
Classifier: Framework :: Zope3
Classifier: License :: OSI Approved :: Zope Public License
Classifier: Programming Language :: Python
Classifier: Natural Language :: English
Classifier: Operating System :: OS Independent
Classifier: Topic :: Internet :: WWW/HTTP
